{
  "products": [
   
    {
      "id": 1,
      "title": "Matte Liquid Lipstick",
      "price": 22.99,
      "offerPrice": 18.99,
      "image": "/kay-nail-polish2.png",
      "images": ["/kay-nail-polish2.png", "/kay-nail-polish2.png", "/kay-nail-polish2.png", "/kay-nail-polish2.png", "/kay-nail-polish2.png"],
      "category": "Makeup",
      "rating": 4.4,
      "testimonials": [
        {
          "name": "Emily R.",
          "text": "The matte lipstick is my new favorite! Stays all day and feels light.",
          "avatar": "/avatar-default.jpg"
        }
      ]
    },
    {
      "id": 3,
      "title": "Volumizing Mascara",
      "price": 19.99,
      "offerPrice": 15.99,
      "image": "/matt1.png",
      "images": ["/matt1.png", "/matt1.png", "/matt1.png", "/matt1.png"],
      "category": "Makeup",
      "rating": 4.1,
      "testimonials": [
        {
          "name": "Jessica P.",
          "text": "Love the volumizing mascara, my lashes look amazing!",
          "avatar": "/avatar-default.jpg"
        }
      ]
    },

    {
      "id": 2,
      "title": "L'Oreal Paris Revitalift Serum",
      "price": 34.99,
      "offerPrice": 29.99,
      "image": "/ce6cb41LOREA00000002_1.jpg",
      "images": ["/ce6cb41LOREA00000002_1.jpg", "/ce6cb41LOREA00000002_1.jpg", "/ce6cb41LOREA00000002_1.jpg", "/ce6cb41LOREA00000002_1.jpg"],
      "category": "Skincare",
      "rating": 5.0,
      "testimonials": [
        {
          "name": "Ashley N.",
          "text": "Hydrating face serum made my skin glow!",
          "avatar": "/avatar-default.jpg"
        }
      ]
    },
    {
      "id": 6,
      "title": "Cerave AM Facial Moisturizing Lotion With Sunscreen",
      "price": 27.99,
      "offerPrice": 22.99,
      "image": "/52690dfCERAV00000044_1a.jpg",
      "images": ["/52690dfCERAV00000044_1a.jpg", "/52690dfCERAV00000044_1a.jpg", "/52690dfCERAV00000044_1a.jpg", "/52690dfCERAV00000044_1a.jpg"],
      "category": "Skincare",
      "rating": 4.5,
      "testimonials": [
        {
          "name": "Lauren P.",
          "text": "Moisturizing day cream is light and non-greasy.",
          "avatar": "/avatar-default.jpg"
        }
      ]
    },

    {
      "id": 4,
      "title": "L'Oreal Paris Extraordinary Oil Nourishing Shampoo",
      "price": 16.99,
      "offerPrice": 12.99,
      "image": "/ace06428901526588978_1.jpg",
      "images": ["/ace06428901526588978_1.jpg", "/ace06428901526588978_1.jpg", "/ace06428901526588978_1.jpg", "/ace06428901526588978_1.jpg"],
      "category": "Haircare",
      "rating": 3.0,
      "testimonials": [
        {
          "name": "Megan M.",
          "text": "Nourishing shampoo made my hair so soft and shiny!",
          "avatar": "/avatar-default.jpg"
        }
      ]
    },
    {
      "id": 8,
      "title": "Livon Style Pro Curl Cream",
      "price": 19.99,
      "offerPrice": 16.99,
      "image": "/ceeb628LIVON00000019_1.jpg",
      "images": ["/ceeb628LIVON00000019_1.jpg", "/ceeb628LIVON00000019_1.jpg", "/ceeb628LIVON00000019_1.jpg", "/ceeb628LIVON00000019_1.jpg"],
      "category": "Haircare",
      "rating": 3.8,
      "testimonials": [
        {
          "name": "Samantha T.",
          "text": "Curl defining cream works wonders for my curls.",
          "avatar": "/avatar-default.jpg"
        }
      ]
    },

  
    {
      "id": 5,
      "title": "Rose Eau de Parfum",
      "price": 59.99,
      "offerPrice": 49.99,
      "image": "/a7531a53614272629370_1.jpg",
      "images": ["/a7531a53614272629370_1.jpg", "/a7531a53614272629370_1.jpg", "/a7531a53614272629370_1.jpg", "/a7531a53614272629370_1.jpg"],
      "category": "Fragrance",
      "rating": 4.8,
      "testimonials": [
        {
          "name": "Rachel V.",
          "text": "Rose Eau de Parfum smells divine and lasts all day.",
          "avatar": "/avatar-default.jpg"
        }
      ]
    },
    {
      "id": 11,
      "title": "Bella Vita Senorita Woman Body Mist",
      "price": 24.99,
      "offerPrice": 19.99,
      "image": "/b506d62BELAB00000378_1.jpg",
      "images": ["/b506d62BELAB00000378_1.jpg", "/b506d62BELAB00000378_1.jpg", "/b506d62BELAB00000378_1.jpg", "/b506d62BELAB00000378_1.jpg"],
      "category": "Fragrance",
      "rating": 4.0,
      "testimonials": [
        {
          "name": "Hannah L.",
          "text": "Floral body mist is so refreshing and light.",
          "avatar": "/avatar-default.jpg"
        }
      ]
    },

    
    {
      "id": 7,
      "title": "MARS Professional Makeup Brush - Set Of 12",
      "price": 39.99,
      "offerPrice": 34.99,
      "image": "/f674195MARSX00000882-new_1.jpg",
      "images": ["/f674195MARSX00000882-new_1.jpg", "/f674195MARSX00000882-new_1.jpg.jpg", "/f674195MARSX00000882-new_1.jpg", "/f674195MARSX00000882-new_1.jpg"],
      "category": "Tools",
      "rating": 4.0,
      "testimonials": []
    },
    {
      "id": 20,
      "title": "Bronson Professional Beauty Blender Sponge Makeup Applicator, Puffs",
      "price": 8.99,
      "offerPrice": 6.99,
      "image": "/e71c2dd7452225850152_1.jpeg",
      "images": ["/e71c2dd7452225850152_1.jpeg", "/e71c2dd7452225850152_1.jpeg", "/e71c2dd7452225850152_1.jpeg", "/e71c2dd7452225850152_1.jpeg"],
      "category": "Tools",
      "rating": 4.4,
      "testimonials": [
        {
          "name": "Olivia T.",
          "text": "Blends foundation flawlessly!",
          "avatar": "/avatar-default.jpg"
        }
      ]
    }
  ]
}
